mn_mpl_style/__init__.py
mn_mpl_style/styles/mn_adi.mplstyle
mn_mpl_style/styles/mn_thesis.mplstyle
mn_mpl_style-0.3.dist-info/licenses/LICENSE
mn_mpl_style-0.3.dist-info/METADATA
mn_mpl_style-0.3.dist-info/WHEEL
mn_mpl_style-0.3.dist-info/top_level.txt
mn_mpl_style-0.3.dist-info/RECORD
