Metadata-Version: 2.4
Name: mn_mpl_style
Version: 0.3
Summary: A collection of custom Matplotlib styles.
Home-page: https://github.com/matt-nagle/mn_mpl_style
Author: Matt Nagle
Author-email: mattnagle96@gmail.com
Classifier: Programming Language :: Python :: 3
Classifier: License :: OSI Approved :: MIT License
Classifier: Operating System :: OS Independent
License-File: LICENSE
Requires-Dist: matplotlib
Dynamic: author
Dynamic: author-email
Dynamic: classifier
Dynamic: description
Dynamic: description-content-type
Dynamic: home-page
Dynamic: license-file
Dynamic: requires-dist
Dynamic: summary
